[{"@id":"419","url":{"#text":"hanakapi-ai-falls-na-pali-coast-kauai"},"title":{"#text":"Hanakapi'ai Falls, Na Pali Coast, Kauai"},"subtitle":{"#text":"Explore the exotic Na Pali coastline in search of secluded beaches and spectacular waterfalls."},"lat":{"#text":"22.220333"},"lon":{"#text":"-159.582535"},"min_lat":{"#text":"22.185974"},"max_lat":{"#text":"22.220333"},"min_lon":{"#text":"-159.597672"},"max_lon":{"#text":"-159.582535"},"num_reviews":{"#text":"10"},"avg_review":{"#text":"4"},"difficulty":{"#text":"Difficult"},"duration":{"#text":"Full day"},"distance":{"#text":"12875"},"dog_friendly":{"#text":0},"family_friendly":{"#text":0},"location":{"#text":"Kilauea, Hawaii, United States"},"rating":{"#text":"0.995389371050344"},"picture":{"thumbnail":{"#text":"http:\/\/images.everytrail.com\/pics\/thumbnail\/1313151-Trailspotting_Logo_for_Everytrail.gif"},"fullsize":{"#text":"http:\/\/images.everytrail.com\/pics\/fullsize\/1313151-Trailspotting_Logo_for_Everytrail.gif"}}},{"@id":"418","url":{"#text":"pihea-amp-alaka-i-swamp-trail-koke-e-sp-kauai"},"title":{"#text":"Pihea & Alaka'i Swamp Trail, Koke'e SP, Kauai"},"subtitle":{"#text":"Combining two of Kauai's best hikes take us from dramatic coastal cliffs to an exotic boardwalked swamp trail."},"lat":{"#text":"22.14742899"},"lon":{"#text":"-159.63136913"},"min_lat":{"#text":"22.14545489"},"max_lat":{"#text":"22.15631247"},"min_lon":{"#text":"-159.64525222778"},"max_lon":{"#text":"-159.59373237"},"num_reviews":{"#text":"3"},"avg_review":{"#text":"5"},"difficulty":{"#text":"Difficult"},"duration":{"#text":"Full day"},"distance":{"#text":"14484"},"dog_friendly":{"#text":0},"family_friendly":{"#text":0},"location":{"#text":"Kilauea, Hawaii, United States"},"rating":{"#text":"0.873570260482807"},"picture":{"thumbnail":{"#text":"http:\/\/images.everytrail.com\/pics\/thumbnail\/1313080-Trailspotting_Logo_for_Everytrail.gif"},"fullsize":{"#text":"http:\/\/images.everytrail.com\/pics\/fullsize\/1313080-Trailspotting_Logo_for_Everytrail.gif"}}}]