[{"@id":"10525","url":{"#text":"chinyero-circular"},"title":{"#text":"Chinyero Circular"},"subtitle":{"#text":"4.2 mile trail in the Teide National Park, Spain"},"lat":{"#text":"28.284398234"},"lon":{"#text":"-16.762201292"},"min_lat":{"#text":"28.284317097"},"max_lat":{"#text":"28.301856145"},"min_lon":{"#text":"-16.766465167"},"max_lon":{"#text":"-16.751703378"},"num_reviews":{"#text":"0"},"avg_review":{"#text":"0"},"difficulty":{"#text":"Easy"},"duration":{"#text":"1-3 hours"},"distance":{"#text":"6759"},"dog_friendly":{"#text":0},"family_friendly":{"#text":0},"location":{"#text":"Santiago del Teide, Canarias, Spain"},"rating":{"#text":"0"},"picture":{"thumbnail":{"#text":"http:\/\/images.everytrail.com\/pics\/thumbnail\/4198562-CRW_7633.jpg"},"fullsize":{"#text":"http:\/\/images.everytrail.com\/pics\/fullsize\/4198562-CRW_7633.jpg"}}}]