[{"@id":"8219","url":{"#text":"circuit-du-patrimoine-montfort-sur-risle"},"title":{"#text":"Circuit du patrimoine Montfort sur Risle"},"subtitle":{"#text":"la Normandie historique dans la vall\u00e9e de la Risle : une balade p\u00e9destre facile \u00e0 la rencontre d\u2019un riche patrimoine."},"lat":{"#text":"49.293938"},"lon":{"#text":"0.665016"},"min_lat":{"#text":"49.293938"},"max_lat":{"#text":"49.299463"},"min_lon":{"#text":"0.659158"},"max_lon":{"#text":"0.667677"},"num_reviews":{"#text":"0"},"avg_review":{"#text":"0"},"difficulty":{"#text":"Moderate"},"duration":{"#text":"1 hour or less"},"distance":{"#text":"2300"},"dog_friendly":{"#text":0},"family_friendly":{"#text":0},"location":{"#text":"Montfort-sur-Risle, Haute-Normandie, France"},"rating":{"#text":"0"},"picture":{"thumbnail":{"#text":"http:\/\/images.everytrail.com\/pics\/thumbnail\/221586-Circuit_du_patrimoine_Montfort_sur_Risle.jpg"},"fullsize":{"#text":"http:\/\/images.everytrail.com\/pics\/fullsize\/221586-Circuit_du_patrimoine_Montfort_sur_Risle.jpg"}}}]