[{"@id":"6520","url":{"#text":"cosan-na-naomh"},"title":{"#text":"Cosan na Naomh"},"subtitle":{"#text":"An old pilgrimage road in Co. Kerry, 18km in length, which takes in breathtaking scenery and important heritage sites."},"lat":{"#text":"52.132645074"},"lon":{"#text":"-10.36390543"},"min_lat":{"#text":"52.1321182115989"},"max_lat":{"#text":"52.214811909"},"min_lon":{"#text":"-10.3833246231079"},"max_lon":{"#text":"-10.291206837"},"num_reviews":{"#text":"1"},"avg_review":{"#text":"5"},"difficulty":{"#text":"Moderate"},"duration":{"#text":"Half day"},"distance":{"#text":"18025"},"dog_friendly":{"#text":0},"family_friendly":{"#text":"1"},"location":{"#text":"Ventry, Munster, Ireland"},"rating":{"#text":"0.193649167310371"},"picture":{"thumbnail":{"#text":"http:\/\/images.everytrail.com\/pics\/thumbnail\/3859877-cosan.jpg"},"fullsize":{"#text":"http:\/\/images.everytrail.com\/pics\/fullsize\/3859877-cosan.jpg"}}},{"@id":"3170","url":{"#text":"ballinrobe-co-mayo-town-heritage-walk"},"title":{"#text":"Ballinrobe, Co. Mayo Town Heritage Walk"},"subtitle":{"#text":"Find some of the 'hidden gems' in Ballinrobe, Co. Mayo. Join us for a walk around this Historic town."},"lat":{"#text":"53.621888121267"},"lon":{"#text":"-9.2231726646423"},"min_lat":{"#text":"53.616542869903"},"max_lat":{"#text":"53.627233372631"},"min_lon":{"#text":"-9.2279577255249"},"max_lon":{"#text":"-9.2183876037598"},"num_reviews":{"#text":"9"},"avg_review":{"#text":"4"},"difficulty":{"#text":"Easy"},"duration":{"#text":"Half day"},"distance":{"#text":"8047"},"dog_friendly":{"#text":"1"},"family_friendly":{"#text":"1"},"location":{"#text":"Ballinrobe, County Mayo, Ireland"},"rating":{"#text":"0.164924225024706"},"picture":{"thumbnail":{"#text":"http:\/\/images.everytrail.com\/pics\/thumbnail\/2599241-Oct_2010__4_.JPG"},"fullsize":{"#text":"http:\/\/images.everytrail.com\/pics\/fullsize\/2599241-Oct_2010__4_.JPG"}}},{"@id":"131429","url":{"#text":"galway-county-garden-trail"},"title":{"#text":"Galway County Garden Trail"},"subtitle":{"#text":"County Galway's rich and varied Horticultural heritage "},"lat":{"#text":"53.29262535"},"lon":{"#text":"-9.1326825651886"},"min_lat":{"#text":"53.0237767"},"max_lat":{"#text":"53.561474"},"min_lon":{"#text":"-10.0469575303772"},"max_lon":{"#text":"-8.21840759999998"},"num_reviews":{"#text":"2"},"avg_review":{"#text":"5"},"difficulty":{"#text":"Easy"},"duration":{"#text":"Multiple days"},"distance":{"#text":"305775"},"dog_friendly":{"#text":0},"family_friendly":{"#text":0},"location":{"#text":"Galway, Ireland"},"rating":{"#text":"0.0866025403784439"},"picture":{"thumbnail":{"#text":"http:\/\/images.everytrail.com\/pics\/thumbnail\/7168648-McGaughs_Galway_Garden_Centre.JPG"},"fullsize":{"#text":"http:\/\/images.everytrail.com\/pics\/fullsize\/7168648-McGaughs_Galway_Garden_Centre.JPG"}}},{"@id":"146961","url":{"#text":"an-cheathr-rua"},"title":{"#text":"An Cheathr\u00fa Rua."},"subtitle":{"#text":"Carraroe "},"lat":{"#text":"53.254502063534"},"lon":{"#text":"-9.6020936965942"},"min_lat":{"#text":"53.2320367874956"},"max_lat":{"#text":"53.2769673395731"},"min_lon":{"#text":"-9.62960243225098"},"max_lon":{"#text":"-9.5745849609375"},"num_reviews":{"#text":"3"},"avg_review":{"#text":"4"},"difficulty":{"#text":"Moderate"},"duration":{"#text":"Full day"},"distance":{"#text":"18507"},"dog_friendly":{"#text":"1"},"family_friendly":{"#text":"1"},"location":{"#text":"An Cheathr\u00fa rua, Co na Gaillimhe, \u00c9IRE"},"rating":{"#text":"0.0824621125123532"},"picture":{"thumbnail":{"#text":"http:\/\/images.everytrail.com\/pics\/thumbnail\/7360651-p122912870-4__1_.jpg"},"fullsize":{"#text":"http:\/\/images.everytrail.com\/pics\/fullsize\/7360651-p122912870-4__1_.jpg"}}},{"@id":"7802","url":{"#text":"golden-mile-mle-rga-lim"},"title":{"#text":"Golden Mile\/M\u00edle \u00d3rga, L\u00e9im"},"subtitle":{"#text":"A stunning walk with breathtaking views of Connemara"},"lat":{"#text":"53.426834193"},"lon":{"#text":"-9.419177771"},"min_lat":{"#text":"53.4246989562116"},"max_lat":{"#text":"53.429340083"},"min_lon":{"#text":"-9.434283972"},"max_lon":{"#text":"-9.419177771"},"num_reviews":{"#text":"0"},"avg_review":{"#text":"0"},"difficulty":{"#text":"Moderate"},"duration":{"#text":"1 hour or less"},"distance":{"#text":"2092"},"dog_friendly":{"#text":"1"},"family_friendly":{"#text":"1"},"location":{"#text":"Leam, Oughterard, Connaught, Ireland"},"rating":{"#text":"0"},"picture":{"thumbnail":{"#text":"http:\/\/images.everytrail.com\/pics\/thumbnail\/3918569-towards_Maam.jpg"},"fullsize":{"#text":"http:\/\/images.everytrail.com\/pics\/fullsize\/3918569-towards_Maam.jpg"}}},{"@id":"7711","url":{"#text":"oughterard-heritage-walk"},"title":{"#text":"Oughterard Heritage Walk"},"subtitle":{"#text":"Historical sites. Local history. Flora and fauna. Along a 1mile (1.6km) award winning walk."},"lat":{"#text":"53.427265702"},"lon":{"#text":"-9.327355027"},"min_lat":{"#text":"53.4204153732481"},"max_lat":{"#text":"53.4276812259147"},"min_lon":{"#text":"-9.338287711"},"max_lon":{"#text":"-9.32376623153686"},"num_reviews":{"#text":"0"},"avg_review":{"#text":"0"},"difficulty":{"#text":"Easy"},"duration":{"#text":"1 hour or less"},"distance":{"#text":"1931"},"dog_friendly":{"#text":"1"},"family_friendly":{"#text":"1"},"location":{"#text":"Oughterard, County Galway, Ireland"},"rating":{"#text":"0"},"picture":{"thumbnail":{"#text":"http:\/\/images.everytrail.com\/pics\/thumbnail\/3909108-walk_start.jpg"},"fullsize":{"#text":"http:\/\/images.everytrail.com\/pics\/fullsize\/3909108-walk_start.jpg"}}},{"@id":"8430","url":{"#text":"ballinrobes-green-walk"},"title":{"#text":"Ballinrobe's 'Green' Walk"},"subtitle":{"#text":"A lovely walk through the old Military Grounds now titled 'The Green'"},"lat":{"#text":"53.618986652105"},"lon":{"#text":"-9.2230224609375"},"min_lat":{"#text":"53.6189866521046"},"max_lat":{"#text":"53.6189866521046"},"min_lon":{"#text":"-9.2230224609375"},"max_lon":{"#text":"-9.2230224609375"},"num_reviews":{"#text":"0"},"avg_review":{"#text":"0"},"difficulty":{"#text":"Easy"},"duration":{"#text":"1-3 hours"},"distance":{"#text":"1609"},"dog_friendly":{"#text":"1"},"family_friendly":{"#text":0},"location":{"#text":"Ballinrobe, County Mayo, Ireland"},"rating":{"#text":"0"},"picture":{"thumbnail":{"#text":"http:\/\/images.everytrail.com\/pics\/thumbnail\/4947624-SW_Infantry_Barracks_and_roadway..jpg"},"fullsize":{"#text":"http:\/\/images.everytrail.com\/pics\/fullsize\/4947624-SW_Infantry_Barracks_and_roadway..jpg"}}},{"@id":"6471","url":{"#text":"siuloid-chuas-na-neighe-clochar-co-kerry-ireland"},"title":{"#text":"Siuloid Chuas na nEighe, Clochar, Co. Kerry, Ireland."},"subtitle":{"#text":"Easy way-marked way (Blue arrows on a white background) near Baile an Fheirtearaigh in West County Kerry, Ireland."},"lat":{"#text":"52.156913501"},"lon":{"#text":"-10.459595919"},"min_lat":{"#text":"52.15117"},"max_lat":{"#text":"52.163034481"},"min_lon":{"#text":"-10.464155674"},"max_lon":{"#text":"-10.453083515"},"num_reviews":{"#text":"0"},"avg_review":{"#text":"0"},"difficulty":{"#text":"Easy"},"duration":{"#text":"1 hour or less"},"distance":{"#text":"2897"},"dog_friendly":{"#text":0},"family_friendly":{"#text":"1"},"location":{"#text":"Clogher, Munster, Ireland"},"rating":{"#text":"0"},"picture":{"thumbnail":{"#text":"http:\/\/images.everytrail.com\/pics\/thumbnail\/4428538-DSC00517.JPG"},"fullsize":{"#text":"http:\/\/images.everytrail.com\/pics\/fullsize\/4428538-DSC00517.JPG"}}},{"@id":"71372","url":{"#text":"source-of-the-blackwater-ballydesmond"},"title":{"#text":"Source of the Blackwater - Ballydesmond"},"subtitle":{"#text":""},"lat":{"#text":"52.206318022"},"lon":{"#text":"-9.288135767"},"min_lat":{"#text":"52.205712777"},"max_lat":{"#text":"52.229566583"},"min_lon":{"#text":"-9.288135767"},"max_lon":{"#text":"-9.250720376"},"num_reviews":{"#text":"0"},"avg_review":{"#text":"0"},"difficulty":{"#text":"unknown"},"duration":{"#text":"unknown"},"distance":{"#text":"11426"},"dog_friendly":{"#text":0},"family_friendly":{"#text":0},"location":{"#text":"Ballydesmond, Munster, Ireland"},"rating":{"#text":"0"},"picture":{"thumbnail":{"#text":"http:\/\/images.everytrail.com\/pics\/thumbnail\/5564888-P1210311_copy.JPG"},"fullsize":{"#text":"http:\/\/images.everytrail.com\/pics\/fullsize\/5564888-P1210311_copy.JPG"}}},{"@id":"6469","url":{"#text":"siuloid-na-cille-dun-chaoin-co-kerry"},"title":{"#text":"Siuloid na Cille, Dun Chaoin, Co. Kerry"},"subtitle":{"#text":"Spectacular way-marked coastal walk in Dun Chaoin, West Kerry, Ireland. This is one of Ireland's National Looped Walks."},"lat":{"#text":"52.13297436"},"lon":{"#text":"-10.461215973"},"min_lat":{"#text":"52.1260324997773"},"max_lat":{"#text":"52.14523523"},"min_lon":{"#text":"-10.468490124"},"max_lon":{"#text":"-10.4535341262817"},"num_reviews":{"#text":"0"},"avg_review":{"#text":"0"},"difficulty":{"#text":"Moderate"},"duration":{"#text":"1-3 hours"},"distance":{"#text":"4506"},"dog_friendly":{"#text":0},"family_friendly":{"#text":"1"},"location":{"#text":"Dunquin, Munster, Ireland"},"rating":{"#text":"0"},"picture":{"thumbnail":{"#text":"http:\/\/images.everytrail.com\/pics\/thumbnail\/3771538-gedc0377.jpg"},"fullsize":{"#text":"http:\/\/images.everytrail.com\/pics\/fullsize\/3771538-gedc0377.jpg"}}}]