[{"@id":"21742","url":{"#text":"ortigas-to-intramuros-by-taxi"},"title":{"#text":"Ortigas to Intramuros by Taxi"},"subtitle":{"#text":""},"lat":{"#text":"14.590540067"},"lon":{"#text":"121.061160564"},"min_lat":{"#text":"14.551995596"},"max_lat":{"#text":"14.612758222"},"min_lon":{"#text":"120.969138333"},"max_lon":{"#text":"121.061396599"},"num_reviews":{"#text":"0"},"avg_review":{"#text":"0"},"difficulty":{"#text":"unknown"},"duration":{"#text":"Full day"},"distance":{"#text":"37015"},"dog_friendly":{"#text":0},"family_friendly":{"#text":0},"location":{"#text":"Quezon City, Metro Manila, Philippines"},"rating":{"#text":"0"},"picture":{"thumbnail":{"#text":"http:\/\/images.everytrail.com\/pics\/thumbnail\/1492405-photo34.jpg"},"fullsize":{"#text":"http:\/\/images.everytrail.com\/pics\/fullsize\/1492405-photo34.jpg"}}},{"@id":"1625","url":{"#text":"tagala-heritage"},"title":{"#text":"Tagala Heritage"},"subtitle":{"#text":"Across Laguna and Quezon towns"},"lat":{"#text":"14.397785"},"lon":{"#text":"121.038799"},"min_lat":{"#text":"13.928733"},"max_lat":{"#text":"14.397785"},"min_lon":{"#text":"121.038262"},"max_lon":{"#text":"121.592666"},"num_reviews":{"#text":"0"},"avg_review":{"#text":"0"},"difficulty":{"#text":"unknown"},"duration":{"#text":"unknown"},"distance":{"#text":"236895"},"dog_friendly":{"#text":0},"family_friendly":{"#text":0},"location":{"#text":"San Pablo, Laguna-Quezon, Philippines"},"rating":{"#text":"0"},"picture":{"thumbnail":{"#text":"http:\/\/images.everytrail.com\/pics\/thumbnail\/2051374-hot_coffee_signage.jpg"},"fullsize":{"#text":"http:\/\/images.everytrail.com\/pics\/fullsize\/2051374-hot_coffee_signage.jpg"}}}]