[{"@id":"1057","url":{"#text":"the-lost-coast"},"title":{"#text":"The Lost Coast Trail"},"subtitle":{"#text":"A 24 mile three day backpacking trip along California's most undeveloped stretch of shoreline."},"lat":{"#text":"40.288995077"},"lon":{"#text":"-124.356104136"},"min_lat":{"#text":"40.044864681"},"max_lat":{"#text":"40.288995077"},"min_lon":{"#text":"-124.363185167"},"max_lon":{"#text":"-124.076923728"},"num_reviews":{"#text":"9"},"avg_review":{"#text":"5"},"difficulty":{"#text":"Moderate"},"duration":{"#text":"Multiple days"},"distance":{"#text":"38624"},"dog_friendly":{"#text":0},"family_friendly":{"#text":0},"location":{"#text":"Petrolia, California, United States"},"rating":{"#text":"0.793331582631122"},"picture":{"thumbnail":{"#text":"http:\/\/images.everytrail.com\/pics\/thumbnail\/1664880-_MG_0440.jpg"},"fullsize":{"#text":"http:\/\/images.everytrail.com\/pics\/fullsize\/1664880-_MG_0440.jpg"}}}]