[{"@id":"1438","url":{"#text":"mt-baker-standard-summit-route"},"title":{"#text":"Mt. Baker Standard Summit Route"},"subtitle":{"#text":"Via Coleman Glacier with optional ski descent"},"lat":{"#text":"48.8019605"},"lon":{"#text":"-121.8962461"},"min_lat":{"#text":"48.7721379"},"max_lat":{"#text":"48.8023542"},"min_lon":{"#text":"-121.8962461"},"max_lon":{"#text":"-121.8145378"},"num_reviews":{"#text":"1"},"avg_review":{"#text":"5"},"difficulty":{"#text":"Difficult"},"duration":{"#text":"Multiple days"},"distance":{"#text":"19473"},"dog_friendly":{"#text":"1"},"family_friendly":{"#text":"1"},"location":{"#text":"Washington, United States"},"rating":{"#text":"0.465698400254929"},"picture":{"thumbnail":{"#text":"http:\/\/images.everytrail.com\/pics\/thumbnail\/1111125-Baker_7-13-08_93.jpg"},"fullsize":{"#text":"http:\/\/images.everytrail.com\/pics\/fullsize\/1111125-Baker_7-13-08_93.jpg"}}},{"@id":"1162","url":{"#text":"artist-point-ski-tours"},"title":{"#text":"Artist Point Ski Tours"},"subtitle":{"#text":"Skiing the Mt. Baker backcountry in deep winter powder or summer corn."},"lat":{"#text":"48.861044546"},"lon":{"#text":"-121.682167053"},"min_lat":{"#text":"48.845400762"},"max_lat":{"#text":"48.861044546"},"min_lon":{"#text":"-121.696157455"},"max_lon":{"#text":"-121.682167053"},"num_reviews":{"#text":"1"},"avg_review":{"#text":"5"},"difficulty":{"#text":"Moderate"},"duration":{"#text":"Half day"},"distance":{"#text":"2414"},"dog_friendly":{"#text":0},"family_friendly":{"#text":0},"location":{"#text":"Mt. Baker Ski Area, Washington, United States"},"rating":{"#text":"0.380788655293195"},"picture":{"thumbnail":{"#text":"http:\/\/images.everytrail.com\/pics\/thumbnail\/1735037-Baker_-_Feb.jpg"},"fullsize":{"#text":"http:\/\/images.everytrail.com\/pics\/fullsize\/1735037-Baker_-_Feb.jpg"}}},{"@id":"1109","url":{"#text":"the-birthday-tour"},"title":{"#text":"The Birthday Tour"},"subtitle":{"#text":"Skiing a classic backcountry tour around Liberty Bell Mountain at Washington Pass"},"lat":{"#text":"48.51893533"},"lon":{"#text":"-120.676531792"},"min_lat":{"#text":"48.496985748"},"max_lat":{"#text":"48.51893533"},"min_lon":{"#text":"-120.676531792"},"max_lon":{"#text":"-120.633101463"},"num_reviews":{"#text":"1"},"avg_review":{"#text":"5"},"difficulty":{"#text":"Difficult"},"duration":{"#text":"Full day"},"distance":{"#text":"8047"},"dog_friendly":{"#text":0},"family_friendly":{"#text":0},"location":{"#text":"Winthrop, Washington, United States"},"rating":{"#text":"0.203100960115899"},"picture":{"thumbnail":{"#text":"http:\/\/images.everytrail.com\/pics\/thumbnail\/1709483-P1000052.JPG"},"fullsize":{"#text":"http:\/\/images.everytrail.com\/pics\/fullsize\/1709483-P1000052.JPG"}}},{"@id":"1163","url":{"#text":"herman-saddle-ski-tour"},"title":{"#text":"Herman Saddle Ski Tour"},"subtitle":{"#text":"Exploring the flanks of Mt. Herman and the basins around Table Mountain"},"lat":{"#text":"48.861439813"},"lon":{"#text":"-121.681995392"},"min_lat":{"#text":"48.853307978"},"max_lat":{"#text":"48.861439813"},"min_lon":{"#text":"-121.723365784"},"max_lon":{"#text":"-121.681995392"},"num_reviews":{"#text":"0"},"avg_review":{"#text":"0"},"difficulty":{"#text":"Moderate"},"duration":{"#text":"Half day"},"distance":{"#text":"9334"},"dog_friendly":{"#text":0},"family_friendly":{"#text":0},"location":{"#text":"Table Mountain, Washington, United States"},"rating":{"#text":"0"},"picture":{"thumbnail":{"#text":"http:\/\/images.everytrail.com\/pics\/thumbnail\/1731874-IMG_0688.JPG"},"fullsize":{"#text":"http:\/\/images.everytrail.com\/pics\/fullsize\/1731874-IMG_0688.JPG"}}},{"@id":"1161","url":{"#text":"table-mountain-ski-tour"},"title":{"#text":"Table Mountain Ski Tour"},"subtitle":{"#text":"Skiing the North Face of Table Mountain in the Mt. Baker Wilderness"},"lat":{"#text":"48.861213946"},"lon":{"#text":"-121.682081223"},"min_lat":{"#text":"48.850060522"},"max_lat":{"#text":"48.861213946"},"min_lon":{"#text":"-121.710748672"},"max_lon":{"#text":"-121.682081223"},"num_reviews":{"#text":"0"},"avg_review":{"#text":"0"},"difficulty":{"#text":"Difficult"},"duration":{"#text":"Half day"},"distance":{"#text":"5472"},"dog_friendly":{"#text":0},"family_friendly":{"#text":0},"location":{"#text":"Table Mountain, Washington, United States"},"rating":{"#text":"0"},"picture":{"thumbnail":{"#text":"http:\/\/images.everytrail.com\/pics\/thumbnail\/1731696-TableMtn-001.JPG"},"fullsize":{"#text":"http:\/\/images.everytrail.com\/pics\/fullsize\/1731696-TableMtn-001.JPG"}}},{"@id":"2249","url":{"#text":"hidden-lake"},"title":{"#text":"Hidden Lake"},"subtitle":{"#text":"This day hike is a thigh-burning 3000+ feet of vertical gain to a fire lookout and stunning mountain views!"},"lat":{"#text":"48.5141052"},"lon":{"#text":"-121.2218508"},"min_lat":{"#text":"48.4951598"},"max_lat":{"#text":"48.5159537"},"min_lon":{"#text":"-121.2218508"},"max_lon":{"#text":"-121.1962568"},"num_reviews":{"#text":"0"},"avg_review":{"#text":"0"},"difficulty":{"#text":"Difficult"},"duration":{"#text":"Full day"},"distance":{"#text":"5955"},"dog_friendly":{"#text":0},"family_friendly":{"#text":0},"location":{"#text":"Marblemount, Washington, United States"},"rating":{"#text":"0"},"picture":{"thumbnail":{"#text":"http:\/\/images.everytrail.com\/pics\/thumbnail\/2389685-IMG_2803.JPG"},"fullsize":{"#text":"http:\/\/images.everytrail.com\/pics\/fullsize\/2389685-IMG_2803.JPG"}}},{"@id":"2259","url":{"#text":"maple-pass-loop"},"title":{"#text":"Maple Pass Loop"},"subtitle":{"#text":"Classic loop hike in the North Cascades, not terribly long but fantastic scenery. Especially beautiful in the fall."},"lat":{"#text":"48.517347005"},"lon":{"#text":"-120.735448122"},"min_lat":{"#text":"48.499314077"},"max_lat":{"#text":"48.517364772"},"min_lon":{"#text":"-120.769340515"},"max_lon":{"#text":"-120.733510494"},"num_reviews":{"#text":"0"},"avg_review":{"#text":"0"},"difficulty":{"#text":"Moderate"},"duration":{"#text":"Half day"},"distance":{"#text":"10300"},"dog_friendly":{"#text":0},"family_friendly":{"#text":0},"location":{"#text":"Gilbert, Washington, United States"},"rating":{"#text":"0"},"picture":{"thumbnail":{"#text":"http:\/\/farm4.static.flickr.com\/3042\/2903876794_19c664acfa_m.jpg"},"fullsize":{"#text":"http:\/\/farm4.static.flickr.com\/3042\/2903876794_19c664acfa.jpg"}}},{"@id":"2247","url":{"#text":"blue-lake-trail-to-dock-butte"},"title":{"#text":"Blue Lake Trail to Dock Butte"},"subtitle":{"#text":"Great Trail for a short day hike with excellent scenery...in late summer the huckleberries are thick."},"lat":{"#text":"48.65420273"},"lon":{"#text":"-121.78450672"},"min_lat":{"#text":"48.64253425"},"max_lat":{"#text":"48.65420273"},"min_lon":{"#text":"-121.80117617"},"max_lon":{"#text":"-121.78442062"},"num_reviews":{"#text":"0"},"avg_review":{"#text":"0"},"difficulty":{"#text":"Moderate"},"duration":{"#text":"1-3 hours"},"distance":{"#text":"3058"},"dog_friendly":{"#text":0},"family_friendly":{"#text":0},"location":{"#text":"Concrete, Washington, United States"},"rating":{"#text":"0"},"picture":{"thumbnail":{"#text":"http:\/\/images.everytrail.com\/pics\/thumbnail\/1984172-Baker_Lake_1.JPG"},"fullsize":{"#text":"http:\/\/images.everytrail.com\/pics\/fullsize\/1984172-Baker_Lake_1.JPG"}}},{"@id":"1226","url":{"#text":"the-rendezvous-mountain-heifer-hut-ski-tour"},"title":{"#text":"The Rendezvous  Mountain - Heifer Hut Ski Tour"},"subtitle":{"#text":"Cross-country skiing tour to the Heifer Hut on Rendezvous Mountain"},"lat":{"#text":"48.571439239"},"lon":{"#text":"-120.217981339"},"min_lat":{"#text":"48.571439239"},"max_lat":{"#text":"48.606581848"},"min_lon":{"#text":"-120.287675858"},"max_lon":{"#text":"-120.217981339"},"num_reviews":{"#text":"0"},"avg_review":{"#text":"0"},"difficulty":{"#text":"Moderate"},"duration":{"#text":"Full day"},"distance":{"#text":"20921"},"dog_friendly":{"#text":0},"family_friendly":{"#text":0},"location":{"#text":"Winthrop, Washington, United States"},"rating":{"#text":"0"},"picture":{"thumbnail":{"#text":"http:\/\/images.everytrail.com\/pics\/thumbnail\/1765668-DSC00323.JPG"},"fullsize":{"#text":"http:\/\/images.everytrail.com\/pics\/fullsize\/1765668-DSC00323.JPG"}}},{"@id":"1473","url":{"#text":"cougar-mountain-ski-tour"},"title":{"#text":"Cougar Mountain Ski Tour"},"subtitle":{"#text":"Climb and ski a local favorite just outside of Winthrop, Washington."},"lat":{"#text":"48.526893969"},"lon":{"#text":"-120.257978439"},"min_lat":{"#text":"48.526893969"},"max_lat":{"#text":"48.545108859039"},"min_lon":{"#text":"-120.2720117569"},"max_lon":{"#text":"-120.256605148"},"num_reviews":{"#text":"0"},"avg_review":{"#text":"0"},"difficulty":{"#text":"Moderate"},"duration":{"#text":"Half day"},"distance":{"#text":"4828"},"dog_friendly":{"#text":0},"family_friendly":{"#text":0},"location":{"#text":"Winthrop, Washington, United States"},"rating":{"#text":"0"},"picture":{"thumbnail":{"#text":"http:\/\/images.everytrail.com\/pics\/thumbnail\/1934646-CougarMtn.jpg"},"fullsize":{"#text":"http:\/\/images.everytrail.com\/pics\/fullsize\/1934646-CougarMtn.jpg"}}},{"@id":"2051","url":{"#text":"gunn-ranch-road-ski-tour"},"title":{"#text":"Gunn Ranch Road Ski Tour"},"subtitle":{"#text":"Cross country skiing high above the Methow Valley with spectacular views and picturesque forest."},"lat":{"#text":"48.526098161"},"lon":{"#text":"-120.258193016"},"min_lat":{"#text":"48.526098161"},"max_lat":{"#text":"48.551387356593"},"min_lon":{"#text":"-120.291237831"},"max_lon":{"#text":"-120.256648064"},"num_reviews":{"#text":"0"},"avg_review":{"#text":"0"},"difficulty":{"#text":"Easy"},"duration":{"#text":"1-3 hours"},"distance":{"#text":"10944"},"dog_friendly":{"#text":0},"family_friendly":{"#text":0},"location":{"#text":"Winthrop, Washington, United States"},"rating":{"#text":"0"},"picture":{"thumbnail":{"#text":"http:\/\/images.everytrail.com\/pics\/thumbnail\/2321363-GR3a.jpg"},"fullsize":{"#text":"http:\/\/images.everytrail.com\/pics\/fullsize\/2321363-GR3a.jpg"}}},{"@id":"2048","url":{"#text":"the-winthrop-trail"},"title":{"#text":"The Winthrop Trail"},"subtitle":{"#text":"Ski the cross country trail from Winthrop to the Sun Mountain trail system and back."},"lat":{"#text":"48.472750562"},"lon":{"#text":"-120.180130005"},"min_lat":{"#text":"48.461539294"},"max_lat":{"#text":"48.475595667"},"min_lon":{"#text":"-120.260467529"},"max_lon":{"#text":"-120.180130005"},"num_reviews":{"#text":"0"},"avg_review":{"#text":"0"},"difficulty":{"#text":"Moderate"},"duration":{"#text":"Full day"},"distance":{"#text":"22531"},"dog_friendly":{"#text":0},"family_friendly":{"#text":0},"location":{"#text":"Winthrop, Washington, United States"},"rating":{"#text":"0"},"picture":{"thumbnail":{"#text":"http:\/\/images.everytrail.com\/pics\/thumbnail\/2315051-S1000001.JPG"},"fullsize":{"#text":"http:\/\/images.everytrail.com\/pics\/fullsize\/2315051-S1000001.JPG"}}}]